mousse.py
pymousse-0.1.5.dist-info/METADATA
pymousse-0.1.5.dist-info/WHEEL
pymousse-0.1.5.dist-info/licenses/LICENCE.md
pymousse-0.1.5.dist-info/RECORD
