Metadata-Version: 2.1
Name: pymousse
Version: 0.1.5
Summary: plagiarism detection using MOSS with post-processing
Project-URL: Homepage, https://github.com/fpom/mousse
Project-URL: Bug Tracker, https://github.com/fpom/mousse/issues
Author-email: Franck Pommereau <franck.pommereau@univ-evry.fr>
License-File: LICENCE.md
Classifier: License :: OSI Approved :: MIT License
Classifier: Operating System :: OS Independent
Classifier: Programming Language :: Python :: 3
Requires-Python: >=3.9
Requires-Dist: beautifulsoup4
Requires-Dist: chardet
Requires-Dist: fastcluster
Requires-Dist: matplotlib
Requires-Dist: mosspy
Requires-Dist: numpy
Requires-Dist: pandas
Requires-Dist: python-levenshtein
Requires-Dist: requests
Requires-Dist: scipy
Requires-Dist: seaborn
Requires-Dist: thefuzz
Requires-Dist: tqdm
